Metadata-Version: 2.1
Name: ftdi-rf
Version: 0.9.7
Summary: Sending and receiving 433/315MHz signals with low-cost GPIO RF modules on a Generic PC, using ftdi serial hardware
Home-page: https://github.com/dpolitis/ftdi-rf
Author: Dimitrios Politis
Author-email: civisd@gmail.com
License: BSD
Keywords: ftdi,rf,gpio,radio,433,433mhz,315,315mhz
Classifier: Development Status :: 4 - Beta
Classifier: Intended Audience :: Developers
Classifier: Topic :: Software Development :: Build Tools
Classifier: License :: OSI Approved :: BSD License
Classifier: Programming Language :: Python :: 3
Classifier: Operating System :: POSIX :: Linux
Classifier: Topic :: Software Development :: Libraries :: Python Modules
License-File: LICENSE.txt
